risk_assessment_package/__init__.py
risk_assessment_package/example.py
risk_assessment_package/main.py
risk_assessment-3.0.0.dist-info/METADATA
risk_assessment-3.0.0.dist-info/WHEEL
risk_assessment-3.0.0.dist-info/entry_points.txt
risk_assessment-3.0.0.dist-info/top_level.txt
risk_assessment-3.0.0.dist-info/RECORD
