Metadata-Version: 2.4
Name: risk-assessment
Version: 3.0.0
Summary: 企业风险评估系统，支持多种风险类型计算、直接相加计算总风险分数、阈值判断和详细计算过程导出
Home-page: https://github.com/yourusername/enterprise-risk-assessment
Author: LT
Author-email: your.email@example.com
Classifier: Programming Language :: Python :: 3
Classifier: License :: OSI Approved :: MIT License
Classifier: Operating System :: OS Independent
Requires-Python: >=3.6
Requires-Dist: pandas>=1.0.0
Requires-Dist: numpy>=1.19.0
Requires-Dist: matplotlib>=3.3.0
Requires-Dist: openpyxl>=3.0.0
Dynamic: author
Dynamic: author-email
Dynamic: classifier
Dynamic: description
Dynamic: description-content-type
Dynamic: home-page
Dynamic: requires-dist
Dynamic: requires-python
Dynamic: summary
